airo_typing/__init__.py
airo_typing/py.typed
airo_typing-2026.1.0.dist-info/METADATA
airo_typing-2026.1.0.dist-info/WHEEL
airo_typing-2026.1.0.dist-info/top_level.txt
airo_typing-2026.1.0.dist-info/RECORD
