Metadata-Version: 2.4
Name: airo_typing
Version: 2026.1.0
Summary: Python type definitions for use in the python packages at the Ghent University AI and Robotics Lab
Author: Thomas Lips
Author-email: thomas.lips@ugent.be
Requires-Dist: numpy>=2.0
Dynamic: author
Dynamic: author-email
Dynamic: requires-dist
Dynamic: summary
